{
  "date": "2026-06-08",
  "day_of_week": "월",
  "theme": "딥다이브 (과학 에디터 피처 / 주초 도달용 바이럴 앵커)",
  "editorial_tone": "경고형(표적 정밀화)",
  "editorial_focus": "SARMs — 'selective(선택적)이라 안전하다'는 첫 거짓말 해체. 이번 주 breakout 클러스터(SARMs 간독성 +11.7pp)에 정밀 탑승, 브랜드 보호미션(10대·청년 입문 차단)과 겹치는 지점. 주말 'STAY NATURAL'(긍정)에서 'FXXK FAKES'(경고)로 복귀하되 표적 정밀화.",
  "focus_keyword": "selective는 안전이 아니다",
  "post": {
    "type": "carousel",
    "version": "viral_v2 (7-card)",
    "best_time": "20:00",
    "best_time_reason": "월요일 인게이지먼트 피크(20:00-22:00). 주초 도달용 바이럴 앵커는 저녁 황금시간 단일 푸시가 최적. 아침 각성 톤은 08:00 스토리 티저로 분리 운용.",
    "hook": "'셀렉티브(선택적)'라서 안전하다고 했다.\n17세 간은 30일 만에 정상의 40배로 타버렸다 — ALT 1662.",
    "caption": "'셀렉티브(선택적)'라서 안전하다고 했다.\n17세 간은 30일 만에 정상의 40배로 타버렸다 — ALT 1662.\n\n'약한 스테로이드'는 없다. SARMs는 입문자가 가장 먼저 속는 첫 관문이다. 이름(selective)이 곧 미끼다.\n\n오늘의 핵심 인텔 (전부 논문 기반)\n\n🔴 1. 17세 / ALT 1662 / 30일 — '셀렉티브라서 안전'이 간을 정상의 40배로 태웠다 (청소년 첫 SARM 간손상 증례)\n\n🔴 2. '혈관 깨끗하니 괜찮다'? 부검은 900g 심장을 꺼냈다 — 관상동맥 멀쩡해도 돌연사\n\n🔴 3. 약을 부른 건 네 의지가 아니라 피드다 — 소년 1,515명, 볼수록 욕망이 커졌다\n\n🔴 4. 경고를 지웠다고 안전 승인은 아니다 — 테스토 사용자 1.3만 명, 무릎수술 후 감염 2.7배 (FDA 경고박스 삭제 ≠ 비의학적 사용 안전)\n\n그래서 오늘 시작할 것 → 약 없이 증명되는 진짜 강함. 거울 속 데피니션은 수명을 1초도 못 늘린다. 손이 쥐는 힘이 늘린다 — 악력 5kg에 사망위험 16%.\n\n📌 저장해두고, 약을 검색하는 친구·동생에게 공유하세요. 매일 업데이트됩니다.\n\n👉 더 많은 팩트 → @nogear.magazine\n🔗 전체 매거진 → nogear-magazine.vercel.app\n\nFXXK FAKES. STAY NATURAL.",
    "cta": "저장 후 공유 — 'selective=안전'을 검색 중인 동생·친구에게 (보호·예방 맥락)",
    "hashtags": {
      "big": ["#헬스", "#보디빌딩", "#피트니스", "#다이어트", "#운동"],
      "mid": ["#스테로이드", "#약물부작용", "#네추럴보디빌딩", "#헬스타그램", "#운동과학", "#건강정보", "#보충제", "#몸스타그램", "#헬스그램", "#운동루틴", "#헬스정보", "#healthylifestyle"],
      "small": ["#SARMs", "#네추럴피지크", "#NOGEAR", "#노기어", "#논문기반", "#스테로이드부작용", "#페이크내추럴", "#약물위험성", "#펩타이드", "#FxxkFakes", "#StayNatural", "#카드뉴스", "#운동뉴스"]
    },
    "hashtag_count": 30,
    "visual_ref": "cardnews/20260608_viral/"
  },
  "secondary_post": {
    "type": "carousel",
    "version": "standard (5-card)",
    "best_time": "08:00 (대안 / A-B 운용 시)",
    "note": "표준 5카드 버전은 피드 보존용 또는 익일 재노출용. 메인은 viral_v2 7카드 단일 푸시 권장(피드 중복 방지).",
    "visual_ref": "cardnews/20260608/"
  },
  "story_ideas": [
    "08:00 아침 티저 — '40배'. 이 숫자 하나만 풀스크린. '오늘 밤 8시, 왜 이게 너의 첫 관문인지.' (저녁 캐러셀 예고)",
    "투표 스티커 — 'SARMs는 스테로이드보다 안전하다?' (예/아니오) → 결과 공개로 신화 붕괴 리빌 (3번 SNS 종단연구 각도와 연결)",
    "공유 유도 슬라이드 — 3번(피드가 약 욕망을 키운다) 단독 스토리, '부모·교사에게 보내기' 멘션 박스 (리치 최대)",
    "21:00 클로저 스토리 — 5번 악력 카드, '그래서 오늘부터 무료로 시작하는 진짜 강함' 링크 스티커"
  ],
  "guardrails": [
    "1번 청소년 증례: 단독 푸시·자극적 표현 금지. 반드시 보호·예방 맥락 안에서만. 실제 인물·환부 이미지 일절 금지(숫자 타이포만).",
    "4번 TRT: 단독 'TRT 안전' 카피 절대 금지. 항상 '적응증 한정 / 안전 승인 아님' 가드와 묶어서만.",
    "톤: 막연한 '위험' 금지 — 항상 '무엇이/어디를/얼마나'(사실·숫자). #STAYNATURAL은 헤드라인 남발 금지, 클로저에만."
  ],
  "weekly_theme_map": {
    "월": "딥다이브 (과학 에디터 피처 / 주초 도달용 바이럴 앵커) — 오늘: 'SARMs: 안전한 스테로이드라는 신화 해부'",
    "화": "스테로이드 팩트 (TOXICITY 독성 청구서)",
    "수": "약물/PED 경고 (정밀 위험 PRECISION RISK 해설형)",
    "목": "자연 피지크 사례 (내추럴 우위 입증)",
    "금": "주간 핫이슈 정리 (THE WEEK IN PED 뉴스 모멘텀)",
    "토": "영양/운동과학 (THE FAKE NATTY ERA 등 패키지 운용)",
    "일": "명예의 전당 리플레이 / STAY NATURAL 긍정 전환"
  },
  "notes": "주초 도달 전략: 저녁 20:00 viral_v2 7카드 단일 캐러셀 + 08:00 '40배' 스토리 티저 + 투표 스티커로 인터랙션 유도. 헤드라인 1번(17세 SARM 간손상 숫자)으로 강하게 열되 선정성 배제. 차주 월요일 딥다이브 1순위 후보: 'STAY NATURAL이 실제로 작동하는 과학(약 없이 증명된 레버 5가지)' + carryover '회복·가역성'."
}
